{"nodes": [{"id": "drawable_icon_app_logo", "label": "Echo Music Logo", "file_type": "image", "source_file": "app/src/main/res/drawable/icon.png", "source_location": null, "source_url": null, "captured_at": null, "author": null, "contributor": null}], "edges": [{"source": "drawable_icon_app_logo", "target": "drawable_echomusicnotification_icon", "relation": "conceptually_related_to", "confidence": "EXTRACTED", "confidence_score": 1.0, "source_file": "app/src/main/res/drawable/icon.png", "source_location": null, "weight": 1.0}, {"source": "drawable_icon_app_logo", "target": "drawable_ic_launcher_foreground_logo", "relation": "shares_data_with", "confidence": "EXTRACTED", "confidence_score": 1.0, "source_file": "app/src/main/res/drawable/icon.png", "source_location": null, "weight": 1.0}], "hyperedges": [{"id": "echo_music_branding", "label": "Echo Music Branding Assets", "nodes": ["drawable_icon_app_logo", "drawable_ic_launcher_foreground_logo", "drawable_ic_launcher_monochrome_logo", "drawable_ic_launcher_nobg_logo", "mipmap_hdpi_ic_launcher_logo"], "relation": "participate_in", "confidence": "INFERRED", "confidence_score": 0.95, "source_file": "app/src/main/res/drawable/icon.png"}]}